setup.py
HTMLTestReport.egg-info/PKG-INFO
HTMLTestReport.egg-info/SOURCES.txt
HTMLTestReport.egg-info/dependency_links.txt
HTMLTestReport.egg-info/top_level.txt
htmltestreport/__init__.py
htmltestreport/core.py
htmltestreport/template.py